README.rst
setup.py
scutils/__init__.py
scutils/argparse_helper.py
scutils/log_factory.py
scutils/method_timer.py
scutils/redis_queue.py
scutils/redis_throttled_queue.py
scutils/settings_wrapper.py
scutils/stats_collector.py
scutils/version.py
scutils/zookeeper_watcher.py
scutils.egg-info/PKG-INFO
scutils.egg-info/SOURCES.txt
scutils.egg-info/dependency_links.txt
scutils.egg-info/requires.txt
scutils.egg-info/top_level.txt
scutils.egg-info/zip-safe