Metadata-Version: 1.0
Name: scutils
Version: 1.3.0.dev4
Summary: Utilities for Scrapy Cluster
Home-page: https://github.com/istresearch/scrapy-cluster
Author: Madison Bahmer
Author-email: madison.bahmer@istresearch.com
License: MIT
Keywords: scrapy,scrapy-cluster,utilities
Platform: UNKNOWN
